README.md
pylisten.py
setup.py
pylisten.egg-info/PKG-INFO
pylisten.egg-info/SOURCES.txt
pylisten.egg-info/dependency_links.txt
pylisten.egg-info/requires.txt
pylisten.egg-info/top_level.txt