Metadata-Version: 1.1
Name: pylisten
Version: 0.1.0
Summary: A simple pyaudio microphone interface
Home-page: https://github.com/mycroftai/pylisten
Author: Matthew Scholefield
Author-email: matthew331199@gmail.com
License: Apache-2.0
Keywords: pyaudio microphone mic
Platform: UNKNOWN
Classifier: Development Status :: 3 - Alpha
Classifier: Intended Audience :: Developers
Classifier: Topic :: Multimedia :: Sound/Audio :: Capture/Recording
Classifier: License :: OSI Approved :: Apache Software License
Classifier: Programming Language :: Python :: 2
Classifier: Programming Language :: Python :: 2.7
Classifier: Programming Language :: Python :: 3
Classifier: Programming Language :: Python :: 3.0
Classifier: Programming Language :: Python :: 3.1
Classifier: Programming Language :: Python :: 3.2
Classifier: Programming Language :: Python :: 3.3
Classifier: Programming Language :: Python :: 3.4
Classifier: Programming Language :: Python :: 3.5
Classifier: Programming Language :: Python :: 3.6
